Metadata-Version: 2.1
Name: pied-piper
Version: 0.0.1
Summary: Awesome Stuff. Not related to compression though...
Home-page: UNKNOWN
Author: Damien "dee" Coureau
License: LGPLv3+
Platform: UNKNOWN
Classifier: Development Status :: 1 - Planning
Classifier: Programming Language :: Python :: 2.7
Classifier: Programming Language :: Python :: 3.7
Classifier: License :: OSI Approved :: GNU Lesser General Public License v3 or later (LGPLv3+)
Requires-Python: >=2.7,!=3.0.*,!=3.1.*,!=3.2.*
Provides-Extra: dev
